LICENCE
MANIFEST.in
README.rst
dev-requirements.txt
requirements.txt
setup.py
weakreflist/__init__.py
weakreflist/testDocExamples.py
weakreflist/testweakreflist.py
weakreflist/weakreflist.py
weakreflist.egg-info/PKG-INFO
weakreflist.egg-info/SOURCES.txt
weakreflist.egg-info/dependency_links.txt
weakreflist.egg-info/top_level.txt
weakreflist.egg-info/zip-safe